shifu_driver/__init__.py
shifu_driver/driver.py
shifu_driver/schema.py
shifu_driver/socket_backend.py
shifu_driver/watchdog.py
shifu_driver-0.1.0.dist-info/LICENSE
shifu_driver-0.1.0.dist-info/METADATA
shifu_driver-0.1.0.dist-info/WHEEL
shifu_driver-0.1.0.dist-info/top_level.txt
shifu_driver-0.1.0.dist-info/RECORD
